constrictor/__init__.py
constrictor/ar.py
constrictor/configreader.py
constrictor/configuration.py
constrictor/control.py
constrictor/dpkg.py
constrictor/helpers.py
deb_constrictor-0.9.data/scripts/constrictor-build
deb_constrictor-0.9.dist-info/LICENSE
deb_constrictor-0.9.dist-info/METADATA
deb_constrictor-0.9.dist-info/WHEEL
deb_constrictor-0.9.dist-info/top_level.txt
deb_constrictor-0.9.dist-info/zip-safe
deb_constrictor-0.9.dist-info/RECORD
