Metadata-Version: 2.1
Name: deb-constrictor
Version: 0.9
Summary: Build DPKGs natively with Python.
Home-page: https://github.com/beneboy/deb-constrictor
Author: Ben Shaw
Author-email: ben@bbit.co.nz
License: BSD 3-Clause
Platform: UNKNOWN
Classifier: Development Status :: 4 - Beta
Classifier: Intended Audience :: Developers
Classifier: Natural Language :: English
Classifier: License :: OSI Approved :: BSD License
Classifier: Programming Language :: Python
Classifier: Programming Language :: Python :: 2.7
Classifier: Programming Language :: Python :: 3.6
